client.py
SalesforceClient/__init__.py
SalesforceClient/client.py
SalesforceClient-1.0.3.dist-info/LICENSE
SalesforceClient-1.0.3.dist-info/METADATA
SalesforceClient-1.0.3.dist-info/WHEEL
SalesforceClient-1.0.3.dist-info/top_level.txt
SalesforceClient-1.0.3.dist-info/RECORD
