Metadata-Version: 2.1
Name: SalesforceClient
Version: 1.0.3
Summary: A python client for Salesforce
Home-page: https://github.com/chaosinside/python-salesforce-client
Author: Chris Hubbard
Author-email: chubbard@gmail.com
License: UNKNOWN
Platform: UNKNOWN
Classifier: Programming Language :: Python :: 3
Classifier: License :: OSI Approved :: MIT License
Classifier: Operating System :: OS Independent
Requires-Python: >=3.6
Requires-Dist: requests
